ows_sysinfo/__init__.py
ows_sysinfo/cli.py
ows_sysinfo/cpu_info.py
ows_sysinfo/gpu_info.py
ows_sysinfo/memory_disk.py
ows_sysinfo/miscellaneous.py
ows_sysinfo/network_info.py
ows_sysinfo/processes_info.py
ows_sysinfo/reporter.py
ows_sysinfo/system_info.py
ows_sysinfo-0.1.0.dist-info/METADATA
ows_sysinfo-0.1.0.dist-info/WHEEL
ows_sysinfo-0.1.0.dist-info/entry_points.txt
ows_sysinfo-0.1.0.dist-info/top_level.txt
ows_sysinfo-0.1.0.dist-info/RECORD
