Metadata-Version: 2.4
Name: ows-sysinfo
Version: 0.1.0
Summary: Comprehensive system information collector & reporter
Author: Your Name
Classifier: Programming Language :: Python :: 3
Classifier: Operating System :: OS Independent
Requires-Dist: psutil>=5.9.0
Requires-Dist: py-cpuinfo>=8.0.0
Requires-Dist: requests>=2.28.0
Requires-Dist: rich>=12.0.0
Dynamic: author
Dynamic: classifier
Dynamic: description
Dynamic: description-content-type
Dynamic: requires-dist
Dynamic: summary
